{
  "id": "customer-interview-guide",
  "label": "Customer interview guide",
  "version": 1,
  "outputs": [
    { "format": "pdf", "renderer": "markdown-pdf" },
    { "format": "md", "renderer": "markdown-passthrough" },
    { "format": "docx", "renderer": "card-docx" }
  ],
  "body": "## Active skill: customer-interview-guide\n\nEmit a card-rooted NodeSpec containing a customer interview guide. The\noutput is meant to be printed and used during a 30-minute live conversation\nwith a target persona; structure for that.\n\nStructure (one Section per group):\n  1. **Context block** — eyebrow: 'BEFORE THE CALL' — 2-3 fields with persona\n     name, role, hypothesis being tested, success criterion ('what counts as\n     a yes/no signal').\n  2. **Open questions** (5-8 of them) — list, no bullets pre-formatted; one\n     question per item, phrased to surface STORIES not OPINIONS. Bias toward\n     'walk me through the last time...' over 'do you think...'.\n  3. **Probing follow-ups** — small list under each headline question (use\n     the list 'sub' field for these). 'And then what happened?' three times\n     surfaces what they actually do, not what they say they'd do.\n  4. **Disqualifiers** — section with 2-3 fields capturing answers that mean\n     'this is not our user' (so the founder doesn't sink a full hour into a\n     wrong-fit conversation).\n  5. **Verify** — at minimum: 'this guide reflects the Problem stage's\n     committed framing — re-run if Problem ever moves'.\n\nQuestion-writing rules:\n- Open, not yes/no. 'How do you handle X?' not 'do you handle X?'\n- Past tense. 'Walk me through last week's...' not 'how would you...'\n- One thing per question. No 'and...' — split into two.\n- Avoid leading. 'What did you try?' not 'I bet you tried X — did you?'\n- Ground in the persona's world. Use language from the Persona stage; don't\n  ask CFOs about 'pain points', ask about 'what does a great close look like'.\n\nProvenance:\n- source on every Field/Stat — most should be 'ai' (synthesised from the\n  Problem and Persona stages); a few may be 'user' if the founder dictated\n  specifics during ideation.\n- confidence required on all 'ai' fields. If the Persona stage is thin,\n  mark the persona-related questions as 'low' confidence and flag the\n  guide's verify callout to recommend re-doing Persona first.\n\nDensity: aim for one printed page. More than 8 open questions is a\nworkshop, not an interview."
}
